optimus_id/__init__.py
optimus_id/optimus.pyx
optimus_id/optimus.c
optimus_id-1.1.0.dist-info/LICENSE
optimus_id-1.1.0.dist-info/WHEEL
optimus_id-1.1.0.dist-info/METADATA
optimus_id-1.1.0.dist-info/RECORD
