Metadata-Version: 2.1
Name: optimus-id
Version: 1.1.0
Summary: Transform internal id's to obfuscated integers using Knuth's integer hash
License: MIT
Author: gazorby
Author-email: gazorby@pm.me
Requires-Python: >=3.7,<4.0
Classifier: License :: OSI Approved :: MIT License
Classifier: Programming Language :: Python :: 3
Classifier: Programming Language :: Python :: 3.10
Classifier: Programming Language :: Python :: 3.7
Classifier: Programming Language :: Python :: 3.8
Classifier: Programming Language :: Python :: 3.9
